rapidminer/__init__.py
rapidminer/rapidminer/__init__.py
rapidminer/rapidminer/core/__init__.py
rapidminer/rapidminer/core/config.py
rapidminer/rapidminer/core/connections.py
rapidminer/rapidminer/core/connector.py
rapidminer/rapidminer/core/oauthenticator.py
rapidminer/rapidminer/core/project.py
rapidminer/rapidminer/core/resources.py
rapidminer/rapidminer/core/scoring.py
rapidminer/rapidminer/core/serdeutils.py
rapidminer/rapidminer/core/server.py
rapidminer/rapidminer/core/studio.py
rapidminer/rapidminer/core/utilities.py
rapidminer/rapidminer/core/web_api.py
rapidminer-2026.0.1.dist-info/licenses/LICENSE
rapidminer-2026.0.1.dist-info/METADATA
rapidminer-2026.0.1.dist-info/WHEEL
rapidminer-2026.0.1.dist-info/top_level.txt
rapidminer-2026.0.1.dist-info/RECORD
