Metadata-Version: 2.4
Name: rapidminer
Version: 2026.0.1
Summary: Tools for running RapidMiner processes and managing RapidMiner repositories.
Author: RapidMiner
License-Expression: AGPL-3.0-or-later
Project-URL: Homepage, https://github.com/rapidminer/python-rapidminer
Project-URL: Repository, https://github.com/rapidminer/python-rapidminer
Project-URL: Documentation, https://github.com/rapidminer/python-rapidminer/tree/master/docs
Project-URL: Bug Tracker, https://github.com/rapidminer/python-rapidminer/issues
Keywords: rapidminer,data-science,machine-learning,analytics
Classifier: Development Status :: 5 - Production/Stable
Classifier: Intended Audience :: Developers
Classifier: Operating System :: OS Independent
Classifier: Programming Language :: Python :: 3
Classifier: Programming Language :: Python :: 3.10
Classifier: Programming Language :: Python :: 3.11
Classifier: Programming Language :: Python :: 3.12
Classifier: Topic :: Scientific/Engineering :: Artificial Intelligence
Classifier: Topic :: Software Development :: Libraries :: Python Modules
Requires-Python: >=3.10
License-File: LICENSE
Requires-Dist: pandas<3.0.0,>=2.2.0
Requires-Dist: requests<3.0.0,>=2.31.0
Requires-Dist: numpy<3.0.0,>=1.24.0
Requires-Dist: zeep<5.0.0,>=4.2.0
Requires-Dist: h5py<4.0.0,>=3.8.0
Requires-Dist: cryptography<50.0.0,>=41.0.0
Requires-Dist: pyjwt<3.0.0,>=2.8.0
Dynamic: license-file
